dbmg.py
dbmg-1.0.0.dist-info/LICENSE.txt
dbmg-1.0.0.dist-info/METADATA
dbmg-1.0.0.dist-info/WHEEL
dbmg-1.0.0.dist-info/RECORD
