Metadata-Version: 2.1
Name: dbmg
Version: 1.0.0
Summary: 
License: MIT
Author: Karl Rittner
Author-email: k.rittner@hotmail.de
Requires-Python: >=3.10,<4.0
Classifier: License :: OSI Approved :: MIT License
Classifier: Programming Language :: Python :: 3
Classifier: Programming Language :: Python :: 3.10
Classifier: Programming Language :: Python :: 3.11
Classifier: Programming Language :: Python :: 3.12
Requires-Dist: pandas (>=2.2.2,<3.0.0)
Requires-Dist: sqlalchemy (>=2.0.30,<3.0.0)
